logng-0.1.3.dist-info/METADATA
logng-0.1.3.dist-info/WHEEL
logng-0.1.3.dist-info/licenses/LICENSE
logng/__init__.py
logng/__version__.py
logng/base/__init__.py
logng/base/enums.py
logng/base/intfs.py
logng/logger.py
logng/outputs.py
logng/shared.py
logng-0.1.3.dist-info/RECORD
