Metadata-Version: 2.1
Name: logng
Version: 0.1.3
Summary: A logging library, intending to simplify the use of logger and easy to configure and implements.
Author-Email: H2Sxxa <h2sxxa0w0@gmail.com>
License: MIT
Classifier: License :: OSI Approved :: MIT License
Classifier: Programming Language :: Python :: 3.8
Classifier: Programming Language :: Python :: 3.9
Classifier: Programming Language :: Python :: 3.10
Classifier: Programming Language :: Python :: 3.11
Project-URL: Homepage, https://pypi.org/project/logng/
Project-URL: Repository, https://github.com/H2Sxxa/logng
Project-URL: Issues, https://github.com/H2Sxxa/logng/issues
Requires-Python: >=3.11
Requires-Dist: colorama
